airiasearch/__init__.py
airiasearch/airiasearch.py
airiasearch/utils.py
airiasearch-0.1.2.dist-info/LICENSE
airiasearch-0.1.2.dist-info/METADATA
airiasearch-0.1.2.dist-info/WHEEL
airiasearch-0.1.2.dist-info/entry_points.txt
airiasearch-0.1.2.dist-info/top_level.txt
airiasearch-0.1.2.dist-info/RECORD
